decthings_model/__init__.py
decthings_model/__main__.py
decthings_model/model.py
decthings_model/run/dataloader.py
decthings_model/run/run.py
decthings_model-0.0.7.dist-info/LICENSE
decthings_model-0.0.7.dist-info/METADATA
decthings_model-0.0.7.dist-info/WHEEL
decthings_model-0.0.7.dist-info/top_level.txt
decthings_model-0.0.7.dist-info/RECORD
