Metadata-Version: 2.1
Name: decthings-model
Version: 0.0.7
Summary: Create a Decthings model using Python
Project-URL: Homepage, https://github.com/decthings/model-py
Classifier: Programming Language :: Python :: 3
Classifier: License :: OSI Approved :: MIT License
Classifier: Operating System :: OS Independent
Requires-Python: >=3.6
License-File: LICENSE
Requires-Dist: decthings-api >=0.0.2
